rename_package_files/__init__.py
rename_package_files-0.1.post1.dist-info/DESCRIPTION.rst
rename_package_files-0.1.post1.dist-info/METADATA
rename_package_files-0.1.post1.dist-info/RECORD
rename_package_files-0.1.post1.dist-info/WHEEL
rename_package_files-0.1.post1.dist-info/metadata.json
rename_package_files-0.1.post1.dist-info/top_level.txt
